<annotation>
	<folder>1267270233</folder>
	<filename>40916.jpg</filename>
	<path>/home/tom/Devel/recall/data/shop_dataset/apparel/men-watches/1267270233/40916.jpg</path>
	<source>
		<database>Unknown</database>
	</source>
	<size>
		<width>360</width>
		<height>640</height>
		<depth>3</depth>
	</size>
	<segmented>0</segmented>
	<object>
		<name>men_watches</name>
		<pose>Unspecified</pose>
		<truncated>0</truncated>
		<difficult>0</difficult>
		<bndbox>
			<xmin>112</xmin>
			<ymin>238</ymin>
			<xmax>274</xmax>
			<ymax>484</ymax>
		</bndbox>
	</object>
</annotation>
