<annotation>
	<folder>train</folder>
	<filename>47327.jpg</filename>
	<path>/home/tom/Downloads/object_detection_demo-master/data/images/train/47327.jpg</path>
	<source>
		<database>Unknown</database>
	</source>
	<size>
		<width>600</width>
		<height>600</height>
		<depth>3</depth>
	</size>
	<segmented>0</segmented>
	<object>
		<name>women-boots</name>
		<pose>Unspecified</pose>
		<truncated>0</truncated>
		<difficult>0</difficult>
		<bndbox>
			<xmin>68</xmin>
			<ymin>82</ymin>
			<xmax>533</xmax>
			<ymax>552</ymax>
		</bndbox>
	</object>
</annotation>
