<annotation>
	<folder>train</folder>
	<filename>63464.jpg</filename>
	<path>/home/tom/Downloads/object_detection_demo-master/data/images/train/63464.jpg</path>
	<source>
		<database>Unknown</database>
	</source>
	<size>
		<width>750</width>
		<height>869</height>
		<depth>3</depth>
	</size>
	<segmented>0</segmented>
	<object>
		<name>men-shoes</name>
		<pose>Unspecified</pose>
		<truncated>0</truncated>
		<difficult>0</difficult>
		<bndbox>
			<xmin>447</xmin>
			<ymin>344</ymin>
			<xmax>693</xmax>
			<ymax>804</ymax>
		</bndbox>
	</object>
	<object>
		<name>men-shoes</name>
		<pose>Unspecified</pose>
		<truncated>0</truncated>
		<difficult>0</difficult>
		<bndbox>
			<xmin>105</xmin>
			<ymin>606</ymin>
			<xmax>417</xmax>
			<ymax>768</ymax>
		</bndbox>
	</object>
</annotation>
